outputstyles/__init__.py
outputstyles/apply_styles.py
outputstyles/msg_type.py
outputstyles/variables.py
outputstyles-1.0.0.dist-info/LICENSE
outputstyles-1.0.0.dist-info/METADATA
outputstyles-1.0.0.dist-info/WHEEL
outputstyles-1.0.0.dist-info/top_level.txt
outputstyles-1.0.0.dist-info/RECORD
