Metadata-Version: 2.1
Name: outputstyles
Version: 1.0.0
Summary: Applying styles to CLI output
Home-page: https://github.com/dunieskysp/output_styles
Author: Duniesky Salazar Pérez
Author-email: <duniesky.salazar@gmail.com>
Keywords: python,outputstyles,CLI styles,text styles
Classifier: Development Status :: 3 - Alpha
Classifier: Programming Language :: Python :: 3
Classifier: Operating System :: MacOS :: MacOS X
Classifier: Operating System :: Microsoft :: Windows
License-File: LICENSE
